Metadata-Version: 2.1
Name: Mensajes-Blurry
Version: 6.0
Summary: Un paquete para saludar y despedir
Home-page: https://www.blurry.dev
Author: Blurry
Author-email: blurry@blurry.dev
Classifier: Environment :: Console
Classifier: Intended Audience :: Developers
Classifier: License :: OSI Approved :: MIT License
Classifier: Operating System :: OS Independent
Classifier: Programming Language :: Python
Classifier: Programming Language :: Python :: 3.12
Classifier: Topic :: Utilities
License-File: LICENSE
Requires-Dist: numpy (>=1.23.1)
